anonymizable_model/__init__.py
anonymizable_model/admin.py
anonymizable_model/apps.py
anonymizable_model/decorators.py
anonymizable_model/settings.py
anonymizable_model/management/__init__.py
anonymizable_model/management/commands/__init__.py
anonymizable_model/management/commands/anonymize_database.py
anonymizable_model/static/css/django_anonimizable_model.css
anonymizable_model/static/js/django_anonimizable_model.js
django_anonymizable_model-0.1.8.dist-info/AUTHORS.rst
django_anonymizable_model-0.1.8.dist-info/LICENSE
django_anonymizable_model-0.1.8.dist-info/METADATA
django_anonymizable_model-0.1.8.dist-info/WHEEL
django_anonymizable_model-0.1.8.dist-info/top_level.txt
django_anonymizable_model-0.1.8.dist-info/RECORD
